{"upload_date": "20141018", "vcodec": "avc1.4d401e", "extractor": "youtube", "series": null, "chapters": null, "height": 360, "like_count": 1, "duration": 238, "fulltitle": "\u5173\u4e8e\u7f8e\u56fd\u4f0a\u6ce2\u62c9\u75c5\u6bd2\u7684\u60c5\u51b5\u548c\u9884\u8b66\uff081\uff09\u7ca4\u8bed", "id": "h2yg_U7jZzU", "album": null, "view_count": 52, "playlist": "Uploads from Faye Hu", "start_time": null, "title": "\u5173\u4e8e\u7f8e\u56fd\u4f0a\u6ce2\u62c9\u75c5\u6bd2\u7684\u60c5\u51b5\u548c\u9884\u8b66\uff081\uff09\u7ca4\u8bed", "_filename": "20141018_NA_h2yg_U7jZzU.mp4", "creator": null, "is_live": null, "playlist_index": 220, "dislike_count": 0, "playlist_id": "UUheuDxi3s2WAefGCbLHwqAw", "abr": 128, "tags": ["\u7f8e\u56fd(\u4f0a\u6ce2\u62c9\uff09America\uff08ebola)"], "uploader_url": "http://www.youtube.com/channel/UCheuDxi3s2WAefGCbLHwqAw", "subtitles": {}, "fps": 30, "stretched_ratio": null, "season_number": null, "annotations": null, "webpage_url_basename": "h2yg_U7jZzU", "acodec": "mp4a.40.2", "display_id": "h2yg_U7jZzU", "automatic_captions": {}, "description": "\u4ecb\u7ecd\u5173\u4e8e\u7f8e\u56fd\u4f0a\u6ce2\u62c9\u75c5\u6bd2\u7684\u6700\u65b0\u60c5\u51b5\u3002\u4e00\u4e9b\u5728\u7f8e\u56fd\u5fb7\u5dde\u8fbe\u62c9\u65af\u5730\u533a\u7684\u6700\u65b0\u6d88\u606f\u3002 \u672c\u9891\u9053\u5c06\u8be6\u7ec6\u4e3a\u4f60\u62a5\u9053\u3002 \u8bf7\u7559\u610f\u4e0b\u4e00\u96c6\u7684\u64ad\u653e\u3002 \u8c22\u8c22\u5173\u6ce8\uff01\uff01", "format": "134 - 640x360 (360p)+140 - audio only (DASH audio)", "track": null, "playlist_uploader": "Faye Hu", "average_rating": null, "uploader": "Faye Hu", "format_id": "134+140", "episode_number": null, "uploader_id": "UCheuDxi3s2WAefGCbLHwqAw", "categories": ["Education"], "playlist_title": "Uploads from Faye Hu", "thumbnails": [{"url": "https://i.ytimg.com/vi/h2yg_U7jZzU/maxresdefault.jpg", "id": "0"}], "license": null, "artist": null, "extractor_key": "Youtube", "release_date": null, "alt_title": null, "channel_id": "UCheuDxi3s2WAefGCbLHwqAw", "thumbnail": "https://i.ytimg.com/vi/h2yg_U7jZzU/maxresdefault.jpg", "vbr": null, "ext": "mp4", "release_year": null, "end_time": null, "webpage_url": "https://www.youtube.com/watch?v=h2yg_U7jZzU", "formats": [{"http_headers": {"Accept-Charset": "ISO-8859-1,utf-8;q=0.7,*;q=0.7", "Accept-Language": "en-us,en;q=0.5", "Accept-Encoding": "gzip, deflate", "Accept": "text/html,application/xhtml+xml,application/xml;q=0.9,*/*;q=0.8", "User-Agent": "Mozilla/5.0 (X11; Linux x86_64; rv:59.0) Gecko/20100101 Firefox/59.0"}, "tbr": 129.033, "container": "m4a_dash", "format": "140 - audio only (DASH audio)", "url": "https://r5---sn-a5m7lnlz.googlevideo.com/videoplayback?id=o-ACUjFV1msmDUyqPgWPKdT8zag_47F0UN6WviX_OcKWLF&itag=140&source=youtube&requiressl=yes&mm=31%2C29&mn=sn-a5m7lnlz%2Csn-a5mekn7d&ms=au%2Crdu&mv=u&pl=21&ei=_fTRXKHPB8GCkwbGvbf4Ag&pcm2=yes&mime=audio%2Fmp4&gir=yes&clen=3783514&dur=238.004&lmt=1515753835062984&mt=1557262903&fvip=1&keepalive=yes&c=WEB&ip=155.94.169.201&ipbits=0&expire=1557285213&sparams=ip%2Cipbits%2Cexpire%2Cid%2Citag%2Csource%2Crequiressl%2Cmm%2Cmn%2Cms%2Cmv%2Cpl%2Cei%2Cpcm2%2Cmime%2Cgir%2Cclen%2Cdur%2Clmt&signature=7AF2F792A92489657058821E619DF867C037F446.05096BCF4BA71BC29E07E336D8A3D57ED0AC918D&key=yt8&ratebypass=yes", "vcodec": "none", "format_note": "DASH audio", "abr": 128, "player_url": "/yts/jsbin/player_ias-vflisCO7O/en_US/base.js", "downloader_options": {"http_chunk_size": 10485760}, "ext": "m4a", "filesize": 3783514, "protocol": "https", "format_id": "140", "quality": -1, "acodec": "mp4a.40.2"}, {"format_note": "360p", "protocol": "https", "format": "134 - 640x360 (360p)", "tbr": 322.333, "height": 360, "downloader_options": {"http_chunk_size": 10485760}, "format_id": "134", "quality": -1, "http_headers": {"Accept-Charset": "ISO-8859-1,utf-8;q=0.7,*;q=0.7", "Accept-Language": "en-us,en;q=0.5", "Accept-Encoding": "gzip, deflate", "Accept": "text/html,application/xhtml+xml,application/xml;q=0.9,*/*;q=0.8", "User-Agent": "Mozilla/5.0 (X11; Linux x86_64; rv:59.0) Gecko/20100101 Firefox/59.0"}, "url": "https://r5---sn-a5m7lnlz.googlevideo.com/videoplayback?id=o-ACUjFV1msmDUyqPgWPKdT8zag_47F0UN6WviX_OcKWLF&aitags=134%2C137&itag=134&source=youtube&requiressl=yes&mm=31%2C29&mn=sn-a5m7lnlz%2Csn-a5mekn7d&ms=au%2Crdu&mv=u&pl=21&ei=_fTRXKHPB8GCkwbGvbf4Ag&pcm2=yes&mime=video%2Fmp4&gir=yes&clen=7853783&dur=237.937&lmt=1515753796410020&mt=1557262903&fvip=1&keepalive=yes&c=WEB&ip=155.94.169.201&ipbits=0&expire=1557285213&sparams=ip%2Cipbits%2Cexpire%2Cid%2Caitags%2Csource%2Crequiressl%2Cmm%2Cmn%2Cms%2Cmv%2Cpl%2Cei%2Cpcm2%2Cmime%2Cgir%2Cclen%2Cdur%2Clmt&signature=061EE8B4160B350D326EA4798555A5E8E1138A8F.3C7920FD427F90164F6D76B3FEE5A9FE7A13E072&key=yt8&ratebypass=yes", "vcodec": "avc1.4d401e", "player_url": "/yts/jsbin/player_ias-vflisCO7O/en_US/base.js", "width": 640, "ext": "mp4", "filesize": 7853783, "fps": 30, "acodec": "none"}, {"format_note": "1080p", "protocol": "https", "format": "137 - 1920x1080 (1080p)", "tbr": 2566.254, "height": 1080, "downloader_options": {"http_chunk_size": 10485760}, "format_id": "137", "quality": -1, "http_headers": {"Accept-Charset": "ISO-8859-1,utf-8;q=0.7,*;q=0.7", "Accept-Language": "en-us,en;q=0.5", "Accept-Encoding": "gzip, deflate", "Accept": "text/html,application/xhtml+xml,application/xml;q=0.9,*/*;q=0.8", "User-Agent": "Mozilla/5.0 (X11; Linux x86_64; rv:59.0) Gecko/20100101 Firefox/59.0"}, "url": "https://r5---sn-a5m7lnlz.googlevideo.com/videoplayback?id=o-ACUjFV1msmDUyqPgWPKdT8zag_47F0UN6WviX_OcKWLF&aitags=134%2C137&itag=137&source=youtube&requiressl=yes&mm=31%2C29&mn=sn-a5m7lnlz%2Csn-a5mekn7d&ms=au%2Crdu&mv=u&pl=21&ei=_fTRXKHPB8GCkwbGvbf4Ag&pcm2=yes&mime=video%2Fmp4&gir=yes&clen=73478394&dur=237.937&lmt=1515753797109425&mt=1557262903&fvip=1&keepalive=yes&c=WEB&ip=155.94.169.201&ipbits=0&expire=1557285213&sparams=ip%2Cipbits%2Cexpire%2Cid%2Caitags%2Csource%2Crequiressl%2Cmm%2Cmn%2Cms%2Cmv%2Cpl%2Cei%2Cpcm2%2Cmime%2Cgir%2Cclen%2Cdur%2Clmt&signature=4AB8313D45FB2271E8591F8323AC64C7E6280E4C.40560B517A55119319A0BDF5A2BA696DA8F6BD1B&key=yt8&ratebypass=yes", "vcodec": "avc1.640028", "player_url": "/yts/jsbin/player_ias-vflisCO7O/en_US/base.js", "width": 1920, "ext": "mp4", "filesize": 73478394, "fps": 30, "acodec": "none"}, {"http_headers": {"Accept-Charset": "ISO-8859-1,utf-8;q=0.7,*;q=0.7", "Accept-Language": "en-us,en;q=0.5", "Accept-Encoding": "gzip, deflate", "Accept": "text/html,application/xhtml+xml,application/xml;q=0.9,*/*;q=0.8", "User-Agent": "Mozilla/5.0 (X11; Linux x86_64; rv:59.0) Gecko/20100101 Firefox/59.0"}, "protocol": "https", "format": "43 - 640x360 (medium)", "url": "https://r5---sn-a5m7lnlz.googlevideo.com/videoplayback?id=o-ACUjFV1msmDUyqPgWPKdT8zag_47F0UN6WviX_OcKWLF&itag=43&source=youtube&requiressl=yes&mm=31%2C29&mn=sn-a5m7lnlz%2Csn-a5mekn7d&ms=au%2Crdu&mv=u&pl=21&ei=_fTRXKHPB8GCkwbGvbf4Ag&pcm2=yes&mime=video%2Fwebm&gir=yes&clen=10134544&ratebypass=yes&dur=0.000&lmt=1515754490246016&mt=1557262903&fvip=1&c=WEB&ip=155.94.169.201&ipbits=0&expire=1557285213&sparams=ip%2Cipbits%2Cexpire%2Cid%2Citag%2Csource%2Crequiressl%2Cmm%2Cmn%2Cms%2Cmv%2Cpl%2Cei%2Cpcm2%2Cmime%2Cgir%2Cclen%2Cratebypass%2Cdur%2Clmt&signature=C0A52D0B31CF11CF557F11A5285F18A7FA813091.D0F327C2EB2E0C23A40ECE87E1B5D02B37F0D4DF&key=yt8", "quality": 1, "vcodec": "vp8.0", "format_note": "medium", "ext": "webm", "player_url": "/yts/jsbin/player_ias-vflisCO7O/en_US/base.js", "width": 640, "abr": 128, "filesize": 10134544, "format_id": "43", "height": 360, "resolution": "640x360", "acodec": "vorbis"}, {"http_headers": {"Accept-Charset": "ISO-8859-1,utf-8;q=0.7,*;q=0.7", "Accept-Language": "en-us,en;q=0.5", "Accept-Encoding": "gzip, deflate", "Accept": "text/html,application/xhtml+xml,application/xml;q=0.9,*/*;q=0.8", "User-Agent": "Mozilla/5.0 (X11; Linux x86_64; rv:59.0) Gecko/20100101 Firefox/59.0"}, "protocol": "https", "format": "18 - 640x360 (medium)", "url": "https://r5---sn-a5m7lnlz.googlevideo.com/videoplayback?id=o-ACUjFV1msmDUyqPgWPKdT8zag_47F0UN6WviX_OcKWLF&itag=18&source=youtube&requiressl=yes&mm=31%2C29&mn=sn-a5m7lnlz%2Csn-a5mekn7d&ms=au%2Crdu&mv=u&pl=21&ei=_fTRXKHPB8GCkwbGvbf4Ag&pcm2=yes&mime=video%2Fmp4&gir=yes&clen=10855864&ratebypass=yes&dur=238.004&lmt=1515753780485277&mt=1557262903&fvip=1&c=WEB&ip=155.94.169.201&ipbits=0&expire=1557285213&sparams=ip%2Cipbits%2Cexpire%2Cid%2Citag%2Csource%2Crequiressl%2Cmm%2Cmn%2Cms%2Cmv%2Cpl%2Cei%2Cpcm2%2Cmime%2Cgir%2Cclen%2Cratebypass%2Cdur%2Clmt&signature=2D55E5930237787DC161CBE578ED06DAA2975265.C5A4A897E5C085E7AEADD7A3787CA4A12C832EA7&key=yt8", "quality": 1, "vcodec": "avc1.42001E", "format_note": "medium", "ext": "mp4", "player_url": "/yts/jsbin/player_ias-vflisCO7O/en_US/base.js", "width": 640, "abr": 96, "filesize": 10855864, "format_id": "18", "height": 360, "resolution": "640x360", "acodec": "mp4a.40.2"}, {"http_headers": {"Accept-Charset": "ISO-8859-1,utf-8;q=0.7,*;q=0.7", "Accept-Language": "en-us,en;q=0.5", "Accept-Encoding": "gzip, deflate", "Accept": "text/html,application/xhtml+xml,application/xml;q=0.9,*/*;q=0.8", "User-Agent": "Mozilla/5.0 (X11; Linux x86_64; rv:59.0) Gecko/20100101 Firefox/59.0"}, "protocol": "https", "format": "22 - 1280x720 (hd720)", "url": "https://r5---sn-a5m7lnlz.googlevideo.com/videoplayback?id=o-ACUjFV1msmDUyqPgWPKdT8zag_47F0UN6WviX_OcKWLF&itag=22&source=youtube&requiressl=yes&mm=31%2C29&mn=sn-a5m7lnlz%2Csn-a5mekn7d&ms=au%2Crdu&mv=u&pl=21&ei=_fTRXKHPB8GCkwbGvbf4Ag&pcm2=yes&mime=video%2Fmp4&ratebypass=yes&dur=238.004&lmt=1515754038130790&mt=1557262903&fvip=1&c=WEB&ip=155.94.169.201&ipbits=0&expire=1557285213&sparams=ip%2Cipbits%2Cexpire%2Cid%2Citag%2Csource%2Crequiressl%2Cmm%2Cmn%2Cms%2Cmv%2Cpl%2Cei%2Cpcm2%2Cmime%2Cratebypass%2Cdur%2Clmt&signature=B5CE4A29431BF7666C8DE02700E1A84BE1EB3830.31D318EA092174646BBB39F745BF967505391A97&key=yt8", "quality": 2, "vcodec": "avc1.64001F", "format_note": "hd720", "ext": "mp4", "player_url": "/yts/jsbin/player_ias-vflisCO7O/en_US/base.js", "width": 1280, "abr": 192, "format_id": "22", "height": 720, "resolution": "1280x720", "acodec": "mp4a.40.2"}], "playlist_uploader_id": "UCheuDxi3s2WAefGCbLHwqAw", "channel_url": "http://www.youtube.com/channel/UCheuDxi3s2WAefGCbLHwqAw", "resolution": null, "width": 640, "n_entries": 227, "age_limit": 0}